myarithmeticpkg5694/__init__.py
myarithmeticpkg5694/arithmetic.py
myarithmeticpkg5694/test_arithmetic.py
myarithmeticpkg5694-0.1.2.dist-info/LICENSE
myarithmeticpkg5694-0.1.2.dist-info/METADATA
myarithmeticpkg5694-0.1.2.dist-info/WHEEL
myarithmeticpkg5694-0.1.2.dist-info/top_level.txt
myarithmeticpkg5694-0.1.2.dist-info/RECORD
