Metadata-Version: 2.1
Name: myarithmeticpkg5694
Version: 0.1.2
Summary: my arithmetic package
Home-page: http://pypi.python.org/pypi/myarithmeticpkg5694/
Author: M.H.M
Author-email: myemail@example.com
License: LICENSE
Platform: UNKNOWN
License-File: LICENSE
Requires-Dist: Django (>=1.1.1)
Requires-Dist: pytest
